dotme/__init__.py
dotme/cli.py
dotme/link.py
dotme/profile.py
dotme/target.py
dotme/utils.py
dotme-0.1.0.dist-info/METADATA
dotme-0.1.0.dist-info/RECORD
dotme-0.1.0.dist-info/WHEEL
dotme-0.1.0.dist-info/top_level.txt
